SNDG/__init__.py
SNDG/ann.py
SNDG/Annotation/CMScan.py
SNDG/Annotation/EMapper.py
SNDG/Annotation/GFFUtils.py
SNDG/Annotation/GenebankUtils.py
SNDG/Annotation/InterPro.py
SNDG/Annotation/Prokka.py
SNDG/Annotation/__init__.py
SNDG/BioMongo/__init__.py
SNDG/BioMongo/Model/Alignment.py
SNDG/BioMongo/Model/DruggabilitySearch.py
SNDG/BioMongo/Model/Feature.py
SNDG/BioMongo/Model/Ontology.py
SNDG/BioMongo/Model/Pathway.py
SNDG/BioMongo/Model/Protein.py
SNDG/BioMongo/Model/ResidueAln.py
SNDG/BioMongo/Model/SeqColDruggabilityParam.py
SNDG/BioMongo/Model/SeqColOntologyIndex.py
SNDG/BioMongo/Model/SeqCollection.py
SNDG/BioMongo/Model/Sequence.py
SNDG/BioMongo/Model/Structure.py
SNDG/BioMongo/Model/Taxonomy.py
SNDG/BioMongo/Model/Variant.py
SNDG/BioMongo/Model/__init__.py
SNDG/BioMongo/Model/exceptions.py
SNDG/BioMongo/Model/variant.py
SNDG/BioMongo/Process/BioCyc2Mongo.py
SNDG/BioMongo/Process/BioDocFactory.py
SNDG/BioMongo/Process/BioMongoDB.py
SNDG/BioMongo/Process/COG2Mongo.py
SNDG/BioMongo/Process/EC2Mongo.py
SNDG/BioMongo/Process/EMapper2Mongo.py
SNDG/BioMongo/Process/GO2Mongo.py
SNDG/BioMongo/Process/Importer.py
SNDG/BioMongo/Process/Index.py
SNDG/BioMongo/Process/KeywordIndexer.py
SNDG/BioMongo/Process/PFAM2Mongo.py
SNDG/BioMongo/Process/PathwaysAnnotator.py
SNDG/BioMongo/Process/SearchLoader.py
SNDG/BioMongo/Process/SeqCollectionLoader.py
SNDG/BioMongo/Process/StructureAnotator.py
SNDG/BioMongo/Process/StructureIndexer.py
SNDG/BioMongo/Process/Taxon.py
SNDG/BioMongo/Process/Variants.py
SNDG/BioMongo/Process/__init__.py
SNDG/Comparative/CoverageAnalysis.py
SNDG/Comparative/MSAMap.py
SNDG/Comparative/Mapping.py
SNDG/Comparative/Mauve.py
SNDG/Comparative/MultiRefCoreAln.py
SNDG/Comparative/Pangenome.py
SNDG/Comparative/Puzzle.py
SNDG/Comparative/ResistanceAnalysis.py
SNDG/Comparative/Saureus.py
SNDG/Comparative/TBDream.py
SNDG/Comparative/Tree.py
SNDG/Comparative/VariantCalling.py
SNDG/Comparative/VariantSet.py
SNDG/Comparative/VcfSnpeffIO.py
sndg_bio-0.1.71.dist-info/LICENSE
sndg_bio-0.1.71.dist-info/METADATA
sndg_bio-0.1.71.dist-info/WHEEL
sndg_bio-0.1.71.dist-info/top_level.txt
sndg_bio-0.1.71.dist-info/RECORD
