Metadata-Version: 2.1
Name: sndg-bio
Version: 0.1.71
Summary: My bioinformatic scripts
Home-page: https://github.com/ezequieljsosa/sndg-bio
Author: Ezequiel Sosa - SNDG
Author-email: ezequieljsosa@gmail.com
License: UNKNOWN
Download-URL: https://github.com/ezequieljsosa/sndg-bio/archive/0.1.tar.gz
Keywords: bioinformatics,sequence,example
Platform: UNKNOWN
Classifier: Programming Language :: Python
Classifier: Topic :: Scientific/Engineering :: Bio-Informatics
Classifier: Intended Audience :: Science/Research
Requires-Dist: bcbio-gff
Requires-Dist: biopython
Requires-Dist: goatools
Requires-Dist: networkx
Requires-Dist: python-libsbml
Requires-Dist: tqdm
